{
  "required": true,
  "minVersion": "0.8.5",
  "package": "com.shinoyuki.slipstream.mixin",
  "compatibilityLevel": "JAVA_17",
  "refmap": "slipstream.refmap.json",
  "mixins": [
    "ChunkMapMixin",
    "ChunkPacketMixin",
    "CompressionEncoderMixin",
    "ConnectionCompressionMixin",
    "ConnectionMixin",
    "PacketEncoderMixin",
    "ServerLoginNegotiationMixin",
    "largepacket.ChunkPacketDataLimitMixin",
    "largepacket.ClientboundCustomPayloadPacketLimitMixin",
    "largepacket.ClientboundCustomQueryPacketLimitMixin",
    "largepacket.CompressionDecoderLimitMixin",
    "largepacket.CompressionEncoderLimitMixin",
    "largepacket.ConnectionReadTimeoutMixin",
    "largepacket.FriendlyByteBufLimitMixin",
    "largepacket.NbtAccounterLimitMixin",
    "largepacket.PacketEncoderLimitMixin",
    "largepacket.ServerGameKeepAliveMixin",
    "largepacket.ServerLoginTimeoutMixin",
    "largepacket.ServerboundCustomPayloadPacketLimitMixin",
    "largepacket.ServerboundCustomQueryPacketLimitMixin",
    "largepacket.Varint21FrameDecoderLimitMixin",
    "largepacket.Varint21LengthFieldPrependerLimitMixin"
  ],
  "client": [
    "ClientHandshakeNegotiationMixin"
  ],
  "server": [],
  "injectors": {
    "defaultRequire": 1
  }
}
